astral_vika/__init__.py
astral_vika/apitable.py
astral_vika/const.py
astral_vika/exceptions.py
astral_vika/request.py
astral_vika/utils.py
astral_vika/datasheet/__init__.py
astral_vika/datasheet/attachment_manager.py
astral_vika/datasheet/datasheet.py
astral_vika/datasheet/datasheet_manager.py
astral_vika/datasheet/field_manager.py
astral_vika/datasheet/query_set.py
astral_vika/datasheet/record.py
astral_vika/datasheet/record_manager.py
astral_vika/datasheet/view_manager.py
astral_vika/node/__init__.py
astral_vika/node/node_manager.py
astral_vika/space/__init__.py
astral_vika/space/space.py
astral_vika/space/space_manager.py
astral_vika/types/__init__.py
astral_vika/types/field_property.py
astral_vika/types/response.py
astral_vika/types/unit_model.py
astral_vika/unit/__init__.py
astral_vika/unit/member.py
astral_vika/unit/role.py
astral_vika/unit/team.py
astral_vika-1.1.4.dist-info/licenses/LICENSE
astral_vika-1.1.4.dist-info/METADATA
astral_vika-1.1.4.dist-info/WHEEL
astral_vika-1.1.4.dist-info/top_level.txt
astral_vika-1.1.4.dist-info/RECORD
