Metadata-Version: 2.4
Name: astral_vika
Version: 1.1.4
Summary: 一个用于与 Vika 维格表 API 交互的 Python 库。
Author-email: astrabot-vika-team <contact@astrabot.com>
License-Expression: MIT
Project-URL: Homepage, https://github.com/AstralSolipsism/astral_vika
Project-URL: Bug Tracker, https://github.com/AstralSolipsism/astral_vika/issues
Keywords: vika,apitable,api,sdk
Classifier: Programming Language :: Python :: 3
Classifier: Operating System :: OS Independent
Classifier: Development Status :: 3 - Alpha
Classifier: Intended Audience :: Developers
Classifier: Topic :: Software Development :: Libraries :: Python Modules
Requires-Python: >=3.8
License-File: LICENSE
Requires-Dist: httpx>=0.23.0
Requires-Dist: anyio<4.0.0,>=3.7.1
Dynamic: license-file
